podRacer/__init__.py
podRacer/_appdata.py
podRacer/download.py
podRacer/download_queue.py
podRacer/organize.py
podRacer/process.py
podRacer/settings.py
podRacer-0.0.1.2.dist-info/METADATA
podRacer-0.0.1.2.dist-info/WHEEL
podRacer-0.0.1.2.dist-info/top_level.txt
podRacer-0.0.1.2.dist-info/RECORD
